emrlauncher/__init__.py
emrlauncher/config_parser.py
emrlauncher/data_loader.py
emrlauncher/emr_launcher.py
emrlauncher/utils.py
aws_emr_launcher-0.1.0.dist-info/LICENSE
aws_emr_launcher-0.1.0.dist-info/METADATA
aws_emr_launcher-0.1.0.dist-info/WHEEL
aws_emr_launcher-0.1.0.dist-info/top_level.txt
aws_emr_launcher-0.1.0.dist-info/RECORD
