Metadata-Version: 2.1
Name: aws-emr-launcher
Version: 0.1.0
Summary: Library that enables to provision EMR clusters with yaml config files (Configuration as Code)
Home-page: https://github.com/HarshadRanganathan/aws-emr-launcher
Author: Harshad Ranganathan
Author-email: rharshad93@gmail.com
License: MIT
Keywords: AWS EMR
Platform: UNKNOWN
Classifier: Programming Language :: Python :: 3.7
Classifier: License :: OSI Approved :: MIT License
Classifier: Operating System :: OS Independent
Classifier: Intended Audience :: Developers
Classifier: Topic :: Software Development :: Libraries :: Python Modules
Requires-Python: >=3.7
Requires-Dist: boto3
